setup.py
yjlab/__init__.py
yjlab/cFunction.py
yjlab.egg-info/PKG-INFO
yjlab.egg-info/SOURCES.txt
yjlab.egg-info/dependency_links.txt
yjlab.egg-info/requires.txt
yjlab.egg-info/top_level.txt