Metadata-Version: 1.0
Name: yjlab
Version: 0.0.1
Summary: isoweek calculation and so on
Home-page: UNKNOWN
Author: joyeonju
Author-email: sue2024@naver.com
License: MIT
Keywords: calendar,isoweek,listsum
Platform: UNKNOWN
